chatchecker/ChatChecker.py
chatchecker/CustomModel.py
chatchecker/Jamo.py
chatchecker/Utils.py
chatchecker/__init__.py
chatchecker/_hangle.py
chatchecker/_index.py
chatchecker/_string_distance.py
chatchecker/clean_dataset.csv
chatchecker/dictionary.txt
chatchecker/final-model.pt
chatchecker/vocab.pt
chatchecker-0.2.6.dist-info/METADATA
chatchecker-0.2.6.dist-info/WHEEL
chatchecker-0.2.6.dist-info/top_level.txt
chatchecker-0.2.6.dist-info/RECORD
