Metadata-Version: 2.1
Name: chatchecker
Version: 0.2.6
Summary: chatchecker
Home-page: https://github.com/seoyoungh/ko-chat-checker
Author: Seoyoung Hong
Author-email: seoyoungh@khu.ac.kr
License: UNKNOWN
Download-URL: https://github.com/seoyoungh/ko-chat-checker
Keywords: chatchecker
Platform: UNKNOWN
Classifier: Programming Language :: Python :: 3
Classifier: Programming Language :: Python :: 3.2
Classifier: Programming Language :: Python :: 3.3
Classifier: Programming Language :: Python :: 3.4
Classifier: Programming Language :: Python :: 3.5
Classifier: Programming Language :: Python :: 3.6
Classifier: Programming Language :: Python :: 3.7
Requires-Python: >=3
Requires-Dist: chatspace
